{"schema_version":"0.1","batch":{"start_source_index":211,"end_source_index":240,"processed_count":30,"created_at":"2026-07-10T06:49:25+09:00"},"policy":{"source_file":"data/org_charlist.csv","source_file_sha":"93194dd072c2f14d013d0e7b9938fb740db7714a","research_policy_sha":"f758f7d90ed1697237dc4a940d20b7cf36cb3d66","note":"Original CSV was not modified. Ambiguous entries are marked needs_review or unresolved. Danbooru tag URLs and official/work URLs are recorded for later low-frequency confirmation."},"results":[{"id":"char_000211_anceril_sacred","source":{"source_index":211,"source_name":"安瑟莉萨克里德（白发教团）","source_tag":"anceril sacred"},"names":{"ja":"アンセリル・セイクリッド","en":"Anceril Sacred","zh":"安瑟莉萨克里德（白发教团）","aliases":[]},"work":{"title_ja":"白髪教団","title_original":"白髪教団","title_en":"White-Haired Church","type":"other","franchise":"white-haired church"},"danbooru":{"character_tag":"anceril_sacred","copyright_tag":"white-haired_church","other_related_tags":[]},"character_info_fields":{"本名":"アンセリル・セイクリッド","備考":"中国語名とDanbooru候補からアンセリル・セイクリッドとして整理。公式日本語表記は要確認。"},"character_info_line":"","sources":[{"type":"danbooru_wiki","url":"https://danbooru.donmai.us/wiki_pages/anceril_sacred"}],"confidence":"medium","status":"needs_review","review_note":"中国語名とDanbooru候補からアンセリル・セイクリッドとして整理。公式日本語表記は要確認。"},{"id":"char_000212_anchorage_azur_lane","source":{"source_index":212,"source_name":"安克雷奇（碧蓝航线）","source_tag":"anchorage (azur lane)"},"names":{"ja":"アンカレッジ","en":"Anchorage","zh":"安克雷奇（碧蓝航线）","aliases":[]},"work":{"title_ja":"アズールレーン","title_original":"アズールレーン","title_en":"Azur Lane","type":"game","franchise":"アズールレーン"},"danbooru":{"character_tag":"anchorage_(azur_lane)","copyright_tag":"azur_lane","other_related_tags":[]},"character_info_fields":{"本名":"アンカレッジ","備考":"アズールレーンの艦船擬人化キャラクター。"},"character_info_line":"","sources":[{"type":"danbooru_wiki","url":"https://danbooru.donmai.us/wiki_pages/anchorage_%28azur_lane%29"},{"type":"official_or_reference","url":"https://azurlane.jp/"}],"confidence":"high","status":"confirmed","review_note":"アズールレーンの艦船擬人化キャラクター。"},{"id":"char_000213_anchovy_girls_und_panzer","source":{"source_index":213,"source_name":"安丘比（少女与战车）","source_tag":"anchovy (girls und panzer)"},"names":{"ja":"アンチョビ","en":"Anchovy","zh":"安丘比（少女与战车）","aliases":[]},"work":{"title_ja":"ガールズ＆パンツァー","title_original":"ガールズ＆パンツァー","title_en":"Girls und Panzer","type":"anime","franchise":"ガールズ＆パンツァー"},"danbooru":{"character_tag":"anchovy_(girls_und_panzer)","copyright_tag":"girls_und_panzer","other_related_tags":[]},"character_info_fields":{"本名":"アンチョビ","備考":"アンツィオ高校の隊長。"},"character_info_line":"","sources":[{"type":"danbooru_wiki","url":"https://danbooru.donmai.us/wiki_pages/anchovy_%28girls_und_panzer%29"},{"type":"official_or_reference","url":"https://girls-und-panzer-finale.jp/"}],"confidence":"high","status":"confirmed","review_note":"アンツィオ高校の隊長。"},{"id":"char_000214_andira_granblue_fantasy","source":{"source_index":214,"source_name":"茵妲拉（碧蓝幻想）","source_tag":"andira (granblue fantasy)"},"names":{"ja":"アンチラ","en":"Andira","zh":"茵妲拉（碧蓝幻想）","aliases":[]},"work":{"title_ja":"グランブルーファンタジー","title_original":"グランブルーファンタジー","title_en":"Granblue Fantasy","type":"game","franchise":"グランブルーファンタジー"},"danbooru":{"character_tag":"andira_(granblue_fantasy)","copyright_tag":"granblue_fantasy","other_related_tags":[]},"character_info_fields":{"本名":"アンチラ","備考":"十二神将の一人。英字表記Andira、日本語表記アンチラ。"},"character_info_line":"","sources":[{"type":"danbooru_wiki","url":"https://danbooru.donmai.us/wiki_pages/andira_%28granblue_fantasy%29"},{"type":"official_or_reference","url":"https://granbluefantasy.jp/"}],"confidence":"high","status":"confirmed","review_note":"十二神将の一人。英字表記Andira、日本語表記アンチラ。"},{"id":"char_000215_andou_girls_und_panzer","source":{"source_index":215,"source_name":"安藤（少女与战车）","source_tag":"andou (girls und panzer)"},"names":{"ja":"安藤","en":"Andou","zh":"安藤（少女与战车）","aliases":[]},"work":{"title_ja":"ガールズ＆パンツァー 最終章","title_original":"ガールズ＆パンツァー 最終章","title_en":"Girls und Panzer das Finale","type":"anime","franchise":"ガールズ＆パンツァー"},"danbooru":{"character_tag":"andou_(girls_und_panzer)","copyright_tag":"girls_und_panzer","other_related_tags":[]},"character_info_fields":{"本名":"安藤","備考":"BC自由学園の登場人物。"},"character_info_line":"","sources":[{"type":"danbooru_wiki","url":"https://danbooru.donmai.us/wiki_pages/andou_%28girls_und_panzer%29"},{"type":"official_or_reference","url":"https://girls-und-panzer-finale.jp/"}],"confidence":"high","status":"confirmed","review_note":"BC自由学園の登場人物。"},{"id":"char_000216_android_18","source":{"source_index":216,"source_name":"人造人18号（龙珠）","source_tag":"android 18"},"names":{"ja":"人造人間18号","en":"Android 18","zh":"人造人18号（龙珠）","aliases":[]},"work":{"title_ja":"ドラゴンボール","title_original":"ドラゴンボール","title_en":"Dragon Ball","type":"manga","franchise":"ドラゴンボール"},"danbooru":{"character_tag":"android_18","copyright_tag":"dragon_ball","other_related_tags":[]},"character_info_fields":{"本名":"人造人間18号","備考":"ドラゴンボールの登場人物。"},"character_info_line":"","sources":[{"type":"danbooru_wiki","url":"https://danbooru.donmai.us/wiki_pages/android_18"},{"type":"official_or_reference","url":"https://dragon-ball-official.com/"}],"confidence":"high","status":"confirmed","review_note":"ドラゴンボールの登場人物。"},{"id":"char_000217_anegasaki_nene","source":{"source_index":217,"source_name":"姉崎宁宁（LovePlus）","source_tag":"anegasaki nene"},"names":{"ja":"姉ヶ崎寧々","en":"Nene Anegasaki","zh":"姉崎宁宁（LovePlus）","aliases":[]},"work":{"title_ja":"ラブプラス","title_original":"ラブプラス","title_en":"LovePlus","type":"game","franchise":"ラブプラス"},"danbooru":{"character_tag":"anegasaki_nene","copyright_tag":"loveplus","other_related_tags":[]},"character_info_fields":{"本名":"姉ヶ崎寧々","備考":"ラブプラスのヒロインの一人。"},"character_info_line":"","sources":[{"type":"danbooru_wiki","url":"https://danbooru.donmai.us/wiki_pages/anegasaki_nene"},{"type":"official_or_reference","url":"https://www.konami.com/games/loveplus/"}],"confidence":"high","status":"confirmed","review_note":"ラブプラスのヒロインの一人。"},{"id":"char_000218_anemone_eureka_seven","source":{"source_index":218,"source_name":"安涅莫妮（交响诗篇）","source_tag":"anemone (eureka seven)"},"names":{"ja":"アネモネ","en":"Anemone","zh":"安涅莫妮（交响诗篇）","aliases":[]},"work":{"title_ja":"交響詩篇エウレカセブン","title_original":"交響詩篇エウレカセブン","title_en":"Eureka Seven","type":"anime","franchise":"エウレカセブン"},"danbooru":{"character_tag":"anemone_(eureka_seven)","copyright_tag":"eureka_seven","other_related_tags":[]},"character_info_fields":{"本名":"アネモネ","備考":"交響詩篇エウレカセブンの登場人物。"},"character_info_line":"","sources":[{"type":"danbooru_wiki","url":"https://danbooru.donmai.us/wiki_pages/anemone_%28eureka_seven%29"},{"type":"official_or_reference","url":"https://eurekaseven.jp/"}],"confidence":"high","status":"confirmed","review_note":"交響詩篇エウレカセブンの登場人物。"},{"id":"char_000219_ange_princess_principal","source":{"source_index":219,"source_name":"安洁（公主准则）","source_tag":"ange (princess principal)"},"names":{"ja":"アンジェ","en":"Ange","zh":"安洁（公主准则）","aliases":[]},"work":{"title_ja":"プリンセス・プリンシパル","title_original":"プリンセス・プリンシパル","title_en":"Princess Principal","type":"anime","franchise":"プリンセス・プリンシパル"},"danbooru":{"character_tag":"ange_(princess_principal)","copyright_tag":"princess_principal","other_related_tags":[]},"character_info_fields":{"本名":"アンジェ","備考":"プリンセス・プリンシパルの主要人物。"},"character_info_line":"","sources":[{"type":"danbooru_wiki","url":"https://danbooru.donmai.us/wiki_pages/ange_%28princess_principal%29"},{"type":"official_or_reference","url":"https://pripri-anime.jp/"}],"confidence":"high","status":"confirmed","review_note":"プリンセス・プリンシパルの主要人物。"},{"id":"char_000220_ange_katrina","source":{"source_index":220,"source_name":"安洁卡特琳娜（彩虹社）","source_tag":"ange katrina"},"names":{"ja":"アンジュ・カトリーナ","en":"Ange Katrina","zh":"安洁卡特琳娜（彩虹社）","aliases":[]},"work":{"title_ja":"にじさんじ","title_original":"にじさんじ","title_en":"Nijisanji","type":"vtuber","franchise":"にじさんじ"},"danbooru":{"character_tag":"ange_katrina","copyright_tag":"nijisanji","other_related_tags":[]},"character_info_fields":{"本名":"アンジュ・カトリーナ","備考":"にじさんじ所属のバーチャルライバー。"},"character_info_line":"","sources":[{"type":"danbooru_wiki","url":"https://danbooru.donmai.us/wiki_pages/ange_katrina"},{"type":"official_or_reference","url":"https://www.nijisanji.jp/talents/l/ange-katrina"}],"confidence":"high","status":"confirmed","review_note":"にじさんじ所属のバーチャルライバー。"},{"id":"char_000221_angel_kof","source":{"source_index":221,"source_name":"安琪尔（拳皇）","source_tag":"angel (kof)"},"names":{"ja":"アンヘル","en":"Angel","zh":"安琪尔（拳皇）","aliases":[]},"work":{"title_ja":"ザ・キング・オブ・ファイターズ","title_original":"ザ・キング・オブ・ファイターズ","title_en":"The King of Fighters","type":"game","franchise":"KOF"},"danbooru":{"character_tag":"angel_(kof)","copyright_tag":"the_king_of_fighters","other_related_tags":[]},"character_info_fields":{"本名":"アンヘル","備考":"KOFシリーズの登場人物。日本語表記はアンヘル。"},"character_info_line":"","sources":[{"type":"danbooru_wiki","url":"https://danbooru.donmai.us/wiki_pages/angel_%28kof%29"},{"type":"official_or_reference","url":"https://www.snk-corp.co.jp/official/kof/"}],"confidence":"high","status":"confirmed","review_note":"KOFシリーズの登場人物。日本語表記はアンヘル。"},{"id":"char_000222_angel_devil_chainsaw_man","source":{"source_index":222,"source_name":"天使恶魔（电锯人）","source_tag":"angel devil (chainsaw man)"},"names":{"ja":"天使の悪魔","en":"Angel Devil","zh":"天使恶魔（电锯人）","aliases":[]},"work":{"title_ja":"チェンソーマン","title_original":"チェンソーマン","title_en":"Chainsaw Man","type":"manga","franchise":"チェンソーマン"},"danbooru":{"character_tag":"angel_devil_(chainsaw_man)","copyright_tag":"chainsaw_man","other_related_tags":[]},"character_info_fields":{"本名":"天使の悪魔","備考":"公安対魔特異4課所属の悪魔。"},"character_info_line":"","sources":[{"type":"danbooru_wiki","url":"https://danbooru.donmai.us/wiki_pages/angel_devil_%28chainsaw_man%29"},{"type":"official_or_reference","url":"https://chainsawman.dog/"}],"confidence":"high","status":"confirmed","review_note":"公安対魔特異4課所属の悪魔。"},{"id":"char_000223_angel_girl_shimmer","source":{"source_index":223,"source_name":"天使少女（Shimmer动画）","source_tag":"angel girl (shimmer)"},"names":{"ja":"天使少女","en":"Angel Girl","zh":"天使少女（Shimmer动画）","aliases":[]},"work":{"title_ja":"Shimmer","title_original":"Shimmer","title_en":"Shimmer","type":"other","franchise":"Shimmer"},"danbooru":{"character_tag":"angel_girl_(shimmer)","copyright_tag":"shimmer","other_related_tags":[]},"character_info_fields":{"本名":"天使少女","備考":"作品・キャラクターの特定根拠が不足。Danbooru候補タグとしてのみ記録。"},"character_info_line":"","sources":[{"type":"danbooru_wiki","url":"https://danbooru.donmai.us/wiki_pages/angel_girl_%28shimmer%29"}],"confidence":"low","status":"unresolved","review_note":"作品・キャラクターの特定根拠が不足。Danbooru候補タグとしてのみ記録。"},{"id":"char_000224_angela_project_moon","source":{"source_index":224,"source_name":"安吉拉（脑叶公司）","source_tag":"angela (project moon)"},"names":{"ja":"アンジェラ","en":"Angela","zh":"安吉拉（脑叶公司）","aliases":[]},"work":{"title_ja":"Lobotomy Corporation","title_original":"Lobotomy Corporation","title_en":"Lobotomy Corporation","type":"game","franchise":"Project Moon"},"danbooru":{"character_tag":"angela_(project_moon)","copyright_tag":"project_moon","other_related_tags":[]},"character_info_fields":{"本名":"アンジェラ","備考":"Project Moon作品群に登場するAIキャラクター。"},"character_info_line":"","sources":[{"type":"danbooru_wiki","url":"https://danbooru.donmai.us/wiki_pages/angela_%28project_moon%29"},{"type":"official_or_reference","url":"https://projectmoon.studio/"}],"confidence":"high","status":"confirmed","review_note":"Project Moon作品群に登場するAIキャラクター。"},{"id":"char_000225_angela_balzac","source":{"source_index":225,"source_name":"安吉拉巴尔扎克（乐园追放）","source_tag":"angela balzac"},"names":{"ja":"アンジェラ・バルザック","en":"Angela Balzac","zh":"安吉拉巴尔扎克（乐园追放）","aliases":[]},"work":{"title_ja":"楽園追放 -Expelled from Paradise-","title_original":"楽園追放 -Expelled from Paradise-","title_en":"Expelled from Paradise","type":"anime","franchise":"楽園追放"},"danbooru":{"character_tag":"angela_balzac","copyright_tag":"rakuen_tsuihou","other_related_tags":[]},"character_info_fields":{"本名":"アンジェラ・バルザック","備考":"映画『楽園追放』の主人公。"},"character_info_line":"","sources":[{"type":"danbooru_wiki","url":"https://danbooru.donmai.us/wiki_pages/angela_balzac"},{"type":"official_or_reference","url":"https://rakuen-tsuiho.com/"}],"confidence":"high","status":"confirmed","review_note":"映画『楽園追放』の主人公。"},{"id":"char_000226_angelia_girls_frontline","source":{"source_index":226,"source_name":"安洁莉娅（少女前线）","source_tag":"angelia (girls' frontline)"},"names":{"ja":"アンジェリア","en":"Angelia","zh":"安洁莉娅（少女前线）","aliases":[]},"work":{"title_ja":"ドールズフロントライン","title_original":"ドールズフロントライン","title_en":"Girls' Frontline","type":"game","franchise":"少女前線"},"danbooru":{"character_tag":"angelia_(girls'_frontline)","copyright_tag":"girls'_frontline","other_related_tags":[]},"character_info_fields":{"本名":"アンジェリア","備考":"少女前線/ドールズフロントラインの登場人物。"},"character_info_line":"","sources":[{"type":"danbooru_wiki","url":"https://danbooru.donmai.us/wiki_pages/angelia_%28girls%27_frontline%29"},{"type":"official_or_reference","url":"https://gf-jp.sunborngame.com/"}],"confidence":"high","status":"confirmed","review_note":"少女前線/ドールズフロントラインの登場人物。"},{"id":"char_000227_angelica_project_moon","source":{"source_index":227,"source_name":"安洁莉卡（脑叶公司）","source_tag":"angelica (project moon)"},"names":{"ja":"アンジェリカ","en":"Angelica","zh":"安洁莉卡（脑叶公司）","aliases":[]},"work":{"title_ja":"Library of Ruina","title_original":"Library of Ruina","title_en":"Library of Ruina","type":"game","franchise":"Project Moon"},"danbooru":{"character_tag":"angelica_(project_moon)","copyright_tag":"project_moon","other_related_tags":[]},"character_info_fields":{"本名":"アンジェリカ","備考":"Project Moon作品群の人物として整理。作品内出典の厳密確認は要継続。"},"character_info_line":"","sources":[{"type":"danbooru_wiki","url":"https://danbooru.donmai.us/wiki_pages/angelica_%28project_moon%29"},{"type":"official_or_reference","url":"https://projectmoon.studio/"}],"confidence":"medium","status":"confirmed","review_note":"Project Moon作品群の人物として整理。作品内出典の厳密確認は要継続。"},{"id":"char_000228_angelina_arknights","source":{"source_index":228,"source_name":"安洁莉娜（明日方舟）","source_tag":"angelina (arknights)"},"names":{"ja":"アンジェリーナ","en":"Angelina","zh":"安洁莉娜（明日方舟）","aliases":[]},"work":{"title_ja":"アークナイツ","title_original":"アークナイツ","title_en":"Arknights","type":"game","franchise":"アークナイツ"},"danbooru":{"character_tag":"angelina_(arknights)","copyright_tag":"arknights","other_related_tags":[]},"character_info_fields":{"本名":"アンジェリーナ","備考":"アークナイツのオペレーター。"},"character_info_line":"","sources":[{"type":"danbooru_wiki","url":"https://danbooru.donmai.us/wiki_pages/angelina_%28arknights%29"},{"type":"official_or_reference","url":"https://www.arknights.jp/"}],"confidence":"high","status":"confirmed","review_note":"アークナイツのオペレーター。"},{"id":"char_000229_angelina_distinguished_visitor_arknights","source":{"source_index":229,"source_name":"安洁莉娜 尊贵访客（明日方舟）","source_tag":"angelina (distinguished visitor) (arknights)"},"names":{"ja":"アンジェリーナ","en":"Angelina","zh":"安洁莉娜 尊贵访客（明日方舟）","aliases":[]},"work":{"title_ja":"アークナイツ","title_original":"アークナイツ","title_en":"Arknights","type":"game","franchise":"アークナイツ"},"danbooru":{"character_tag":"angelina_(distinguished_visitor)_(arknights)","copyright_tag":"arknights","other_related_tags":[]},"character_info_fields":{"本名":"アンジェリーナ","備考":"アンジェリーナの衣装差分タグ。日本語衣装名の公式表記は要確認。"},"character_info_line":"","sources":[{"type":"danbooru_wiki","url":"https://danbooru.donmai.us/wiki_pages/angelina_%28distinguished_visitor%29_%28arknights%29"},{"type":"official_or_reference","url":"https://www.arknights.jp/"}],"confidence":"medium","status":"needs_review","review_note":"アンジェリーナの衣装差分タグ。日本語衣装名の公式表記は要確認。"},{"id":"char_000230_angelina_summer_flower_arknights","source":{"source_index":230,"source_name":"安洁莉娜 夏卉（明日方舟）","source_tag":"angelina (summer flower) (arknights)"},"names":{"ja":"アンジェリーナ","en":"Angelina","zh":"安洁莉娜 夏卉（明日方舟）","aliases":[]},"work":{"title_ja":"アークナイツ","title_original":"アークナイツ","title_en":"Arknights","type":"game","franchise":"アークナイツ"},"danbooru":{"character_tag":"angelina_(summer_flower)_(arknights)","copyright_tag":"arknights","other_related_tags":[]},"character_info_fields":{"本名":"アンジェリーナ","備考":"アンジェリーナの夏衣装差分タグ。日本語衣装名の公式表記は要確認。"},"character_info_line":"","sources":[{"type":"danbooru_wiki","url":"https://danbooru.donmai.us/wiki_pages/angelina_%28summer_flower%29_%28arknights%29"},{"type":"official_or_reference","url":"https://www.arknights.jp/"}],"confidence":"medium","status":"needs_review","review_note":"アンジェリーナの夏衣装差分タグ。日本語衣装名の公式表記は要確認。"},{"id":"char_000231_angewomon","source":{"source_index":231,"source_name":"天女兽（数码宝贝）","source_tag":"angewomon"},"names":{"ja":"エンジェウーモン","en":"Angewomon","zh":"天女兽（数码宝贝）","aliases":[]},"work":{"title_ja":"デジモンアドベンチャー","title_original":"デジモンアドベンチャー","title_en":"Digimon Adventure","type":"anime","franchise":"デジモン"},"danbooru":{"character_tag":"angewomon","copyright_tag":"digimon","other_related_tags":[]},"character_info_fields":{"本名":"エンジェウーモン","備考":"デジモンシリーズの完全体デジモン。"},"character_info_line":"","sources":[{"type":"danbooru_wiki","url":"https://danbooru.donmai.us/wiki_pages/angewomon"},{"type":"official_or_reference","url":"https://digimon.net/"}],"confidence":"high","status":"confirmed","review_note":"デジモンシリーズの完全体デジモン。"},{"id":"char_000232_anila_granblue_fantasy","source":{"source_index":232,"source_name":"阿妮拉（碧蓝幻想）","source_tag":"anila (granblue fantasy)"},"names":{"ja":"アニラ","en":"Anila","zh":"阿妮拉（碧蓝幻想）","aliases":[]},"work":{"title_ja":"グランブルーファンタジー","title_original":"グランブルーファンタジー","title_en":"Granblue Fantasy","type":"game","franchise":"グランブルーファンタジー"},"danbooru":{"character_tag":"anila_(granblue_fantasy)","copyright_tag":"granblue_fantasy","other_related_tags":[]},"character_info_fields":{"本名":"アニラ","備考":"十二神将の一人。"},"character_info_line":"","sources":[{"type":"danbooru_wiki","url":"https://danbooru.donmai.us/wiki_pages/anila_%28granblue_fantasy%29"},{"type":"official_or_reference","url":"https://granbluefantasy.jp/"}],"confidence":"high","status":"confirmed","review_note":"十二神将の一人。"},{"id":"char_000233_anis_nikke","source":{"source_index":233,"source_name":"阿妮斯（胜利女神：妮姬）","source_tag":"anis (nikke)"},"names":{"ja":"アニス","en":"Anis","zh":"阿妮斯（胜利女神：妮姬）","aliases":[]},"work":{"title_ja":"勝利の女神：NIKKE","title_original":"勝利の女神：NIKKE","title_en":"Goddess of Victory: NIKKE","type":"game","franchise":"NIKKE"},"danbooru":{"character_tag":"anis_(nikke)","copyright_tag":"goddess_of_victory:_nikke","other_related_tags":[]},"character_info_fields":{"本名":"アニス","備考":"カウンターズ所属のニケ。"},"character_info_line":"","sources":[{"type":"danbooru_wiki","url":"https://danbooru.donmai.us/wiki_pages/anis_%28nikke%29"},{"type":"official_or_reference","url":"https://nikke-jp.com/"}],"confidence":"high","status":"confirmed","review_note":"カウンターズ所属のニケ。"},{"id":"char_000234_anis_sparkling_summer_nikke","source":{"source_index":234,"source_name":"阿妮斯 夏日闪耀（胜利女神：妮姬）","source_tag":"anis (sparkling summer) (nikke)"},"names":{"ja":"アニス：スパークリングサマー","en":"Anis: Sparkling Summer","zh":"阿妮斯 夏日闪耀（胜利女神：妮姬）","aliases":[]},"work":{"title_ja":"勝利の女神：NIKKE","title_original":"勝利の女神：NIKKE","title_en":"Goddess of Victory: NIKKE","type":"game","franchise":"NIKKE"},"danbooru":{"character_tag":"anis_(sparkling_summer)_(nikke)","copyright_tag":"goddess_of_victory:_nikke","other_related_tags":[]},"character_info_fields":{"本名":"アニス：スパークリングサマー","備考":"アニスの水着バージョン/衣装差分。"},"character_info_line":"","sources":[{"type":"danbooru_wiki","url":"https://danbooru.donmai.us/wiki_pages/anis_%28sparkling_summer%29_%28nikke%29"},{"type":"official_or_reference","url":"https://nikke-jp.com/"}],"confidence":"high","status":"confirmed","review_note":"アニスの水着バージョン/衣装差分。"},{"id":"char_000235_anise_tatlin_tales_of_abyss","source":{"source_index":235,"source_name":"阿尼斯·塔特琳（深渊传说）","source_tag":"anise tatlin (tales of abyss)"},"names":{"ja":"アニス・タトリン","en":"Anise Tatlin","zh":"阿尼斯·塔特琳（深渊传说）","aliases":[]},"work":{"title_ja":"テイルズ オブ ジ アビス","title_original":"テイルズ オブ ジ アビス","title_en":"Tales of the Abyss","type":"game","franchise":"テイルズ オブ"},"danbooru":{"character_tag":"anise_tatlin_(tales_of_abyss)","copyright_tag":"tales_of_the_abyss","other_related_tags":[]},"character_info_fields":{"本名":"アニス・タトリン","備考":"テイルズ オブ ジ アビスのパーティキャラクター。"},"character_info_line":"","sources":[{"type":"danbooru_wiki","url":"https://danbooru.donmai.us/wiki_pages/anise_tatlin_%28tales_of_abyss%29"},{"type":"official_or_reference","url":"https://tales-ch.jp/"}],"confidence":"high","status":"confirmed","review_note":"テイルズ オブ ジ アビスのパーティキャラクター。"},{"id":"char_000236_anisphia_wynn_palettia","source":{"source_index":236,"source_name":"安尼斯菲亚·温·帕莱提亚（转生公主与天才女士的魔法革命）","source_tag":"anisphia wynn palettia"},"names":{"ja":"アニスフィア・ウィン・パレッティア","en":"Anisphia Wynn Palettia","zh":"安尼斯菲亚·温·帕莱提亚（转生公主与天才女士的魔法革命）","aliases":[]},"work":{"title_ja":"転生王女と天才令嬢の魔法革命","title_original":"転生王女と天才令嬢の魔法革命","title_en":"The Magical Revolution of the Reincarnated Princess and the Genius Young Lady","type":"light_novel","franchise":"転生王女と天才令嬢の魔法革命"},"danbooru":{"character_tag":"anisphia_wynn_palettia","copyright_tag":"tensei_oujo_to_tensai_reijou_no_mahou_kakumei","other_related_tags":[]},"character_info_fields":{"本名":"アニスフィア・ウィン・パレッティア","備考":"同作の主人公。"},"character_info_line":"","sources":[{"type":"danbooru_wiki","url":"https://danbooru.donmai.us/wiki_pages/anisphia_wynn_palettia"},{"type":"official_or_reference","url":"https://tenten-kakumei.com/"}],"confidence":"high","status":"confirmed","review_note":"同作の主人公。"},{"id":"char_000237_anjou_naruko","source":{"source_index":237,"source_name":"安城鸣子（未闻花名）","source_tag":"anjou naruko"},"names":{"ja":"安城鳴子","en":"Naruko Anjou","zh":"安城鸣子（未闻花名）","aliases":[]},"work":{"title_ja":"あの日見た花の名前を僕達はまだ知らない。","title_original":"あの日見た花の名前を僕達はまだ知らない。","title_en":"Anohana: The Flower We Saw That Day","type":"anime","franchise":"あの花"},"danbooru":{"character_tag":"anjou_naruko","copyright_tag":"ano_hi_mita_hana_no_namae_wo_bokutachi_wa_mada_shiranai","other_related_tags":[]},"character_info_fields":{"本名":"安城鳴子","備考":"通称あなる。キャラ情報では本名を記録。"},"character_info_line":"","sources":[{"type":"danbooru_wiki","url":"https://danbooru.donmai.us/wiki_pages/anjou_naruko"},{"type":"official_or_reference","url":"https://www.anohana.jp/"}],"confidence":"high","status":"confirmed","review_note":"通称あなる。キャラ情報では本名を記録。"},{"id":"char_000238_ankha_animal_crossing","source":{"source_index":238,"source_name":"尼罗（动物森友会）","source_tag":"ankha (animal crossing)"},"names":{"ja":"ナイル","en":"Ankha","zh":"尼罗（动物森友会）","aliases":[]},"work":{"title_ja":"どうぶつの森","title_original":"どうぶつの森","title_en":"Animal Crossing","type":"game","franchise":"どうぶつの森"},"danbooru":{"character_tag":"ankha_(animal_crossing)","copyright_tag":"animal_crossing","other_related_tags":[]},"character_info_fields":{"本名":"ナイル","備考":"どうぶつの森シリーズのネコ住民。英語名Ankha、日本語名ナイル。"},"character_info_line":"","sources":[{"type":"danbooru_wiki","url":"https://danbooru.donmai.us/wiki_pages/ankha_%28animal_crossing%29"},{"type":"official_or_reference","url":"https://www.nintendo.com/jp/character/mori/"}],"confidence":"high","status":"confirmed","review_note":"どうぶつの森シリーズのネコ住民。英語名Ankha、日本語名ナイル。"},{"id":"char_000239_anko_gochiusa","source":{"source_index":239,"source_name":"安子（请问您今天要来点兔子吗？）","source_tag":"anko (gochiusa)"},"names":{"ja":"あんこ","en":"Anko","zh":"安子（请问您今天要来点兔子吗？）","aliases":[]},"work":{"title_ja":"ご注文はうさぎですか？","title_original":"ご注文はうさぎですか？","title_en":"Is the Order a Rabbit?","type":"manga","franchise":"ご注文はうさぎですか？"},"danbooru":{"character_tag":"anko_(gochiusa)","copyright_tag":"gochuumon_wa_usagi_desu_ka?","other_related_tags":[]},"character_info_fields":{"本名":"あんこ","備考":"作中の動物キャラクターとして整理。"},"character_info_line":"","sources":[{"type":"danbooru_wiki","url":"https://danbooru.donmai.us/wiki_pages/anko_%28gochiusa%29"},{"type":"official_or_reference","url":"https://gochiusa.com/"}],"confidence":"medium","status":"confirmed","review_note":"作中の動物キャラクターとして整理。"},{"id":"char_000240_anna_frozen","source":{"source_index":240,"source_name":"安娜（冰雪奇缘）","source_tag":"anna (frozen)"},"names":{"ja":"アナ","en":"Anna","zh":"安娜（冰雪奇缘）","aliases":[]},"work":{"title_ja":"アナと雪の女王","title_original":"アナと雪の女王","title_en":"Frozen","type":"anime","franchise":"ディズニー"},"danbooru":{"character_tag":"anna_(frozen)","copyright_tag":"frozen","other_related_tags":[]},"character_info_fields":{"本名":"アナ","備考":"ディズニー映画『アナと雪の女王』の主人公の一人。"},"character_info_line":"","sources":[{"type":"danbooru_wiki","url":"https://danbooru.donmai.us/wiki_pages/anna_%28frozen%29"},{"type":"official_or_reference","url":"https://www.disney.co.jp/movie/anayuki"}],"confidence":"high","status":"confirmed","review_note":"ディズニー映画『アナと雪の女王』の主人公の一人。"}]}